instappt/__init__.py
instappt/_version.py
instappt/cli.py
instappt/core.py
instappt/models.py
instappt/prompts.py
instappt/ui.py
instappt/utils.py
instappt-0.0.2.dist-info/licenses/LICENSE
instappt-0.0.2.dist-info/METADATA
instappt-0.0.2.dist-info/WHEEL
instappt-0.0.2.dist-info/entry_points.txt
instappt-0.0.2.dist-info/top_level.txt
instappt-0.0.2.dist-info/RECORD
