Metadata-Version: 2.4
Name: instappt
Version: 0.0.2
Summary: Add your description here
Requires-Python: >=3.12
License-File: LICENSE
Requires-Dist: openai>=2.9.0
Requires-Dist: openpyxl>=3.1.5
Requires-Dist: pandas>=2.3.3
Requires-Dist: pydantic>=2.12.5
Requires-Dist: python-pptx>=1.0.2
Requires-Dist: reportlab>=4.4.5
Requires-Dist: tqdm>=4.67.1
Requires-Dist: gradio>=4.0.0
Requires-Dist: pypdf>=3.16.2
Requires-Dist: requests>=2.32.3
Dynamic: license-file
